ocp_practice_gu/__init__.py
ocp_practice_gu/ocp_helper.py
ocp_practice_gu-0.0.1.dist-info/LICENSE
ocp_practice_gu-0.0.1.dist-info/METADATA
ocp_practice_gu-0.0.1.dist-info/WHEEL
ocp_practice_gu-0.0.1.dist-info/top_level.txt
ocp_practice_gu-0.0.1.dist-info/RECORD
