Metadata-Version: 2.1
Name: ocp-practice-gu
Version: 0.0.1
Summary: Quick start for ocp-catalysis
Home-page: https://github.com/GuGroup/ocp-practice-gu
Author: Geun Ho Gu
Author-email: googhgoo@hotmail.com
Classifier: Programming Language :: Python :: 3
Classifier: License :: OSI Approved :: MIT License
Classifier: Operating System :: OS Independent
License-File: LICENSE
